[
    { "id": 1, "name": "Bonebreaker Bob", "lat": 37.7749, "lng": -122.4194, "description": "Specializes in ethically questionable cuts at unbeatable prices." },
    { "id": 2, "name": "Cleaver Carl", "lat": 41.8818, "lng": -87.6231, "description": "Known for their 'anything goes' approach to meat procurement." },
    { "id": 3, "name": "The Crimson Cleaver", "lat": 25.7617, "lng": -80.1882, "description": "Offers a wide variety of exotic meats, some you might not want to ask about." },
    { "id": 7, "name": "The Tenderizer", "lat": -33.8688,"lng": 151.2093, "description": "Their methods are a mystery, but their meat is undeniably tender." },
    { "id": 11, "name": "The Bone Yard", "lat": 55.7558, "lng": 37.6176, "description": "Specializes in 'aged' meats. Very aged." },
    { "id": 12, "name": "The Crimson Claw", "lat": 60.1719, "lng": 24.9666, "description": "Claims their meat is sourced 'ethically.' Don't believe the hype." },
    { "id": 14, "name": "The Meat Cleaver", "lat": 52.3730, "lng": 4.8951, "description": "Known for their 'no questions asked' policy." },
    { "id": 15, "name": "The Chop Shop", "lat": 48.8566, "lng": 2.3522, "description": "Their motto: 'From farm to table... eventually.'" },  
    { "id": 17, "name": "Cleaver Carl", "lat": 29.9792, "lng": 31.1302, "description": "Specializes in 'custom cuts.' Just don't ask what the custom is." }
]  