{
  "ilveganoimbruttito": [
    {
      "question": "Which year have you become vegan?",
      "correctAnswer": "2015"
    },
    {
      "question": "Which day were you born?",
      "correctAnswer": "10th December"
    },
    {
      "question": "In which town have you attended elementary school?",
      "correctAnswer": "Santilario"
    }
  ],
  "fabioladisotto": [
    {
      "question": "What month was your first child born?",
      "correctAnswer": "March"
    },
    {
      "question": "What month did you get married?",
      "correctAnswer": "September"
    },
    {
      "question": "What month has your brother gotten married?",
      "correctAnswer": "December"
    }
  ]
}